kisi/__init__.py
kisi/kisi.py
kisi/kisi_old.py
Kisi-1.4.dist-info/LICENSE
Kisi-1.4.dist-info/METADATA
Kisi-1.4.dist-info/WHEEL
Kisi-1.4.dist-info/top_level.txt
Kisi-1.4.dist-info/RECORD
