Metadata-Version: 2.1
Name: Kisi
Version: 1.4
Summary: A python package for Kisi API
Author-email: Ankush Kumar <ankush1611996@gmail.com>
Project-URL: Homepage, https://github.com/AnkushRozra/Kisi
Project-URL: Bug Tracker, https://github.com/AnkushRozra/Kisi/issues
Keywords: Kisi,KISI door,KISI,Kisi lock,getkisi,Kisi modern access control,Kisi python library
Classifier: Programming Language :: Python :: 3
Classifier: License :: OSI Approved :: MIT License
Classifier: Operating System :: OS Independent
Requires-Python: >=3.8
License-File: LICENSE
Requires-Dist: requests
